vlccast/__init__.py
vlccast/server.py
vlccast/static/index.html
vlccast/static/js/.app.js.swp
vlccast/static/js/app.js
vlccast/static/views/googleauth.html
vlccast/static/views/player.html
vlccast/static/views/youtube/index.html
vlccast/static/views/youtube/list.html
vlccast/static/views/youtube/search.html
vlccast-0.3.0.dist-info/DESCRIPTION.rst
vlccast-0.3.0.dist-info/METADATA
vlccast-0.3.0.dist-info/RECORD
vlccast-0.3.0.dist-info/WHEEL
vlccast-0.3.0.dist-info/entry_points.txt
vlccast-0.3.0.dist-info/metadata.json
vlccast-0.3.0.dist-info/top_level.txt
