Metadata-Version: 2.0
Name: vlccast
Version: 0.3.0
Summary: Watch videos using web interface using vlc
Home-page: https://github.com/matematik7/vlccast
Author: Domen Ipavec
Author-email: domen@ipavec.net
License: MIT
Keywords: vlc video web
Platform: UNKNOWN
Classifier: Development Status :: 3 - Alpha
Classifier: License :: OSI Approved :: MIT License
Classifier: Programming Language :: Python :: 2
Classifier: Programming Language :: Python :: 2.6
Classifier: Programming Language :: Python :: 2.7
Classifier: Programming Language :: Python :: 3
Classifier: Programming Language :: Python :: 3.3
Classifier: Programming Language :: Python :: 3.4
Classifier: Programming Language :: Python :: 3.5
Requires-Dist: Flask
Requires-Dist: youtube-dl
Provides-Extra: dev
Requires-Dist: check-manifest; extra == 'dev'
Provides-Extra: test
Requires-Dist: coverage; extra == 'test'
